qt_style_sheet_inspector/__init__.py
qt_style_sheet_inspector/_inspector.py
qt_style_sheet_inspector-0.1.0.dist-info/METADATA
qt_style_sheet_inspector-0.1.0.dist-info/RECORD
qt_style_sheet_inspector-0.1.0.dist-info/WHEEL
qt_style_sheet_inspector-0.1.0.dist-info/top_level.txt
