Metadata-Version: 2.1
Name: qt-style-sheet-inspector
Version: 0.1.0
Summary: A inspector widget to view and modify style sheet of a Qt app in runtime.
Home-page: https://github.com/ESSS/qt_style_sheet_inspector
Author: Rafael Bertoldi
Author-email: tochaman@gmail.com
License: MIT license
Keywords: qt_style_sheet_inspector
Platform: UNKNOWN
Classifier: Development Status :: 2 - Pre-Alpha
Classifier: Intended Audience :: Developers
Classifier: License :: OSI Approved :: MIT License
Classifier: Natural Language :: English
Classifier: Programming Language :: Python :: 2
Classifier: Programming Language :: Python :: 2.7
Classifier: Programming Language :: Python :: 3
Classifier: Programming Language :: Python :: 3.4
Classifier: Programming Language :: Python :: 3.5
Classifier: Programming Language :: Python :: 3.6
